fixed_docxtpl.py
docxtpldjufix/__init__.py
docxtpldjufix/setup.py
docxtpldjufix/template.py
docxtpldjufix/EVERYTHING_DOCXTPL/six.py
docxtpldjufix/EVERYTHING_DOCXTPL/typing_extensions.py
docxtpldjufix/EVERYTHING_DOCXTPL/_distutils_hack/__init__.py
docxtpldjufix/EVERYTHING_DOCXTPL/_distutils_hack/override.py
docxtpldjufix/EVERYTHING_DOCXTPL/babel/__init__.py
docxtpldjufix/EVERYTHING_DOCXTPL/babel/core.py
docxtpldjufix/EVERYTHING_DOCXTPL/babel/dates.py
docxtpldjufix/EVERYTHING_DOCXTPL/babel/languages.py
docxtpldjufix/EVERYTHING_DOCXTPL/babel/lists.py
docxtpldjufix/EVERYTHING_DOCXTPL/babel/localedata.py
docxtpldjufix/EVERYTHING_DOCXTPL/babel/numbers.py
docxtpldjufix/EVERYTHING_DOCXTPL/babel/plural.py
docxtpldjufix/EVERYTHING_DOCXTPL/babel/py.typed
docxtpldjufix/EVERYTHING_DOCXTPL/babel/support.py
docxtpldjufix/EVERYTHING_DOCXTPL/babel/units.py
docxtpldjufix/EVERYTHING_DOCXTPL/babel/util.py
docxtpldjufix/EVERYTHING_DOCXTPL/babel/localtime/__init__.py
docxtpldjufix/EVERYTHING_DOCXTPL/babel/localtime/_fallback.py
docxtpldjufix/EVERYTHING_DOCXTPL/babel/localtime/_helpers.py
docxtpldjufix/EVERYTHING_DOCXTPL/babel/localtime/_unix.py
docxtpldjufix/EVERYTHING_DOCXTPL/babel/localtime/_win32.py
docxtpldjufix/EVERYTHING_DOCXTPL/babel/messages/__init__.py
docxtpldjufix/EVERYTHING_DOCXTPL/babel/messages/_compat.py
docxtpldjufix/EVERYTHING_DOCXTPL/babel/messages/catalog.py
docxtpldjufix/EVERYTHING_DOCXTPL/babel/messages/checkers.py
docxtpldjufix/EVERYTHING_DOCXTPL/babel/messages/extract.py
docxtpldjufix/EVERYTHING_DOCXTPL/babel/messages/frontend.py
docxtpldjufix/EVERYTHING_DOCXTPL/babel/messages/jslexer.py
docxtpldjufix/EVERYTHING_DOCXTPL/babel/messages/mofile.py
docxtpldjufix/EVERYTHING_DOCXTPL/babel/messages/plurals.py
docxtpldjufix/EVERYTHING_DOCXTPL/babel/messages/pofile.py
docxtpldjufix/EVERYTHING_DOCXTPL/babel/messages/setuptools_frontend.py
docxtpldjufix/EVERYTHING_DOCXTPL/docx/__init__.py
docxtpldjufix/EVERYTHING_DOCXTPL/docx/api.py
docxtpldjufix-1.1.dist-info/licenses/LICENSE.txt
docxtpldjufix-1.1.dist-info/METADATA
docxtpldjufix-1.1.dist-info/WHEEL
docxtpldjufix-1.1.dist-info/top_level.txt
docxtpldjufix-1.1.dist-info/RECORD
