Metadata-Version: 2.4
Name: docxtpldjufix
Version: 1.1
Summary: Fixed through properties docxtpl library, no more deprecated pkg_resources
Project-URL: homepage, https://github.com/elapouya/python-docx-template
Project-URL: repository, https://github.com/elapouya/python-docx-template.git
Project-URL: document, https://docxtpl.readthedocs.org
Keywords: jinja2
Classifier: Programming Language :: Python :: 3
Classifier: Operating System :: Microsoft :: Windows
Requires-Python: >=3.10
License-File: LICENSE.txt
Requires-Dist: python-docx
Requires-Dist: jinja2
Requires-Dist: lxml
Provides-Extra: subdoc
Requires-Dist: docxcompose; extra == "subdoc"
Provides-Extra: docs
Requires-Dist: Sphinx; extra == "docs"
Requires-Dist: sphinxcontrib-napoleon; extra == "docs"
Dynamic: license-file
